sadel-0.1.1.dist-info/METADATA
sadel-0.1.1.dist-info/WHEEL
sadel-0.1.1.dist-info/entry_points.txt
sadel-0.1.1.dist-info/licenses/LICENSE
sadel/__init__.py
sadel/base.py
sadel-0.1.1.dist-info/RECORD
