Metadata-Version: 2.1
Name: sadel
Version: 0.1.1
Summary: Helper class for upserting records to database
Author-Email: =?utf-8?q?Dani=C3=ABl_Tom?= <d.e.tom89@gmail.com>
Requires-Python: >=3.10
Requires-Dist: sqlmodel<0.1.0,>=0.0.21
